wrapp/__init__.py
wrapp/wrapp.py
wrapp-0.7.0.dist-info/LICENSE
wrapp-0.7.0.dist-info/METADATA
wrapp-0.7.0.dist-info/WHEEL
wrapp-0.7.0.dist-info/entry_points.txt
wrapp-0.7.0.dist-info/RECORD
